incubig_raven.py
incubig_raven-1.0.1.dist-info/METADATA
incubig_raven-1.0.1.dist-info/WHEEL
incubig_raven-1.0.1.dist-info/top_level.txt
incubig_raven-1.0.1.dist-info/RECORD
