Metadata-Version: 2.1
Name: incubig-raven
Version: 1.0.1
Summary: This module is send secure communication to clients
Author-email: Ketan Chandra <ketan@incubig.org>
Project-URL: Homepage, https://github.com/IncubigInnovations/communication/incubig-raven
Project-URL: Bug Tracker, https://github.com/IncubigInnovations/communication/issues
Classifier: Programming Language :: Python :: 3
Classifier: License :: OSI Approved :: MIT License
Classifier: Operating System :: OS Independent
Requires-Python: >=3.6
Requires-Dist: azure-communication-email
Requires-Dist: python-decouple
